{
    "increase_prev": {
        "pcurve": {
            "prevdiff_exp": 0.20260190147491286,
            "prevdiff_hdi": [
                -0.12746015388196696,
                0.5761156200148403
            ],
            "prevdiff_prob": 0.8668,
            "powdiff_exp": 0.11766439341342355,
            "powdiff_hdi": [
                -0.1491170949095178,
                0.37294870561697196
            ],
            "powdiff_prob": 0.814
        },
        "binom": {
            "prevdiff_exp": 0.14965665711288625,
            "prevdiff_hdi": [
                -0.4163530545531227,
                0.6808775977880356
            ],
            "prevdiff_prob": 0.6946,
            "powdiff_exp": 0.15089786664808813,
            "powdiff_hdi": [
                -0.37586251276460314,
                0.6580555930080574
            ],
            "powdiff_prob": 0.7124
        },
        "pval_group": 0.041015625,
        "frac_H1_rej": 0.48148148148148145
    },
    "increase_pow": {
        "pcurve": {
            "prevdiff_exp": -0.17049410687968541,
            "prevdiff_hdi": [
                -0.5951421546668245,
                0.28391205724306157
            ],
            "prevdiff_prob": 0.2286,
            "powdiff_exp": 0.2261407604966721,
            "powdiff_hdi": [
                -0.1133888065329785,
                0.5940405654026324
            ],
            "powdiff_prob": 0.885
        },
        "binom": {
            "prevdiff_exp": 0.02452377634934167,
            "prevdiff_hdi": [
                -0.5849800262113836,
                0.6351628926091069
            ],
            "prevdiff_prob": 0.5358,
            "powdiff_exp": 0.03360243236014403,
            "powdiff_hdi": [
                -0.5689434114861476,
                0.6196204902599365
            ],
            "powdiff_prob": 0.5512
        },
        "pval_group": 0.169921875,
        "frac_H1_rej": 0.9
    },
    "baseline": {
        "frac_H1_rej": 0.4666666666666667
    }
}