{
    "increase_prev": {
        "pcurve": {
            "prevdiff_exp": 0.3545865066108332,
            "prevdiff_hdi": [
                -0.11230442727696688,
                0.8308517508439306
            ],
            "prevdiff_prob": 0.8856,
            "powdiff_exp": 0.11388052120997032,
            "powdiff_hdi": [
                -0.3718273196553188,
                0.48210292565834023
            ],
            "powdiff_prob": 0.727
        },
        "binom": {
            "prevdiff_exp": 0.3129470726300418,
            "prevdiff_hdi": [
                -0.2942382312327132,
                0.8330186748847063
            ],
            "prevdiff_prob": 0.835,
            "powdiff_exp": 0.3135087874880802,
            "powdiff_hdi": [
                -0.25540657363523656,
                0.8309854336949258
            ],
            "powdiff_prob": 0.8376
        },
        "pval_group": 0.001953125,
        "frac_H1_rej": 0.5862068965517241
    },
    "increase_pow": {
        "pcurve": {
            "prevdiff_exp": 0.11749532137386202,
            "prevdiff_hdi": [
                -0.3792153760105534,
                0.5721717674805753
            ],
            "prevdiff_prob": 0.6636,
            "powdiff_exp": 0.45201300765485775,
            "powdiff_hdi": [
                -0.023277700061791418,
                0.7738426877203316
            ],
            "powdiff_prob": 0.9552
        },
        "binom": {
            "prevdiff_exp": 0.35511012887856314,
            "prevdiff_hdi": [
                -0.20588124458997492,
                0.8461788116823477
            ],
            "prevdiff_prob": 0.8636,
            "powdiff_exp": 0.35098791043688116,
            "powdiff_hdi": [
                -0.22356966656867416,
                0.8045328741841651
            ],
            "powdiff_prob": 0.877
        },
        "pval_group": 0.0234375,
        "frac_H1_rej": 1.0
    },
    "baseline": {
        "frac_H1_rej": 0.3333333333333333
    }
}