{
    "increase_prev": {
        "pcurve": {
            "prevdiff_exp": 0.19334686375732232,
            "prevdiff_hdi": [
                -0.2369705675962619,
                0.7085871742084722
            ],
            "prevdiff_prob": 0.7764,
            "powdiff_exp": 0.13831646678462609,
            "powdiff_hdi": [
                -0.10325781281299296,
                0.37210369684030775
            ],
            "powdiff_prob": 0.8896
        },
        "binom": {
            "prevdiff_exp": 0.23092088461642374,
            "prevdiff_hdi": [
                -0.4763117388619527,
                0.8469370303267065
            ],
            "prevdiff_prob": 0.7632,
            "powdiff_exp": 0.24576658550695565,
            "powdiff_hdi": [
                -0.3890052468682567,
                0.8430022403459646
            ],
            "powdiff_prob": 0.7844
        },
        "pval_group": 0.01171875,
        "frac_H1_rej": 0.35714285714285715
    },
    "increase_pow": {
        "pcurve": {
            "prevdiff_exp": -0.1211116183297808,
            "prevdiff_hdi": [
                -0.545220606701492,
                0.37665224439742867
            ],
            "prevdiff_prob": 0.3022,
            "powdiff_exp": 0.47183179714496,
            "powdiff_hdi": [
                0.20655735798533842,
                0.737855049365712
            ],
            "powdiff_prob": 0.9934
        },
        "binom": {
            "prevdiff_exp": 0.3471760472951625,
            "prevdiff_hdi": [
                -0.2666603518363327,
                0.9234581379003726
            ],
            "prevdiff_prob": 0.8452,
            "powdiff_exp": 0.36055487007165826,
            "powdiff_hdi": [
                -0.2380676433303308,
                0.8696746718182069
            ],
            "powdiff_prob": 0.8674
        },
        "pval_group": 0.2255859375,
        "frac_H1_rej": 1.0
    },
    "baseline": {
        "frac_H1_rej": 0.2
    }
}