{
    "increase_prev": {
        "pcurve": {
            "prevdiff_exp": 0.4043480222543285,
            "prevdiff_hdi": [
                0.012428784449185791,
                0.7412121445597551
            ],
            "prevdiff_prob": 0.9732,
            "powdiff_exp": -0.012835768853865056,
            "powdiff_hdi": [
                -0.3963749581850231,
                0.35246699494365186
            ],
            "powdiff_prob": 0.483
        },
        "pval_group": 0.041015625,
        "frac_H1_rej": 0.37037037037037035
    },
    "increase_pow": {
        "pcurve": {
            "prevdiff_exp": 0.06099119236117373,
            "prevdiff_hdi": [
                -0.20799607091889039,
                0.3398557757160955
            ],
            "prevdiff_prob": 0.6666,
            "powdiff_exp": 0.19913362278541977,
            "powdiff_hdi": [
                -0.17635403201697974,
                0.550487088830641
            ],
            "powdiff_prob": 0.8506
        },
        "pval_group": 0.583984375,
        "frac_H1_rej": 0.9166666666666666
    },
    "baseline": {
        "frac_H1_rej": 0.6666666666666666
    }
}